rb/__init__.py
rb/complexity/__init__.py
rb/complexity/complexity_index.py
rb/complexity/index_category.py
rb/complexity/measure_function.py
rb/complexity/cohesion/__init__.py
rb/complexity/cohesion/adj_cohesion.py
rb/complexity/cohesion/factory.py
rb/complexity/morphology/__init__.py
rb/complexity/morphology/factory.py
rb/complexity/morphology/pos_main.py
rb/complexity/morphology/unq_pos_main.py
rb/complexity/surface/__init__.py
rb/complexity/surface/ch_entropy.py
rb/complexity/surface/ch_ngram_entropy.py
rb/complexity/surface/factory.py
rb/complexity/surface/no_cacophonies.py
rb/complexity/surface/no_commas.py
rb/complexity/surface/no_common_errors.py
rb/complexity/surface/no_punctuations.py
rb/complexity/surface/no_sentences.py
rb/complexity/surface/no_unq_words.py
rb/complexity/surface/no_words.py
rb/complexity/surface/wd_entropy.py
rb/complexity/syntax/__init__.py
rb/complexity/syntax/dep.py
rb/complexity/syntax/dep_enum.py
rb/complexity/syntax/factory.py
rb/complexity/syntax/parse_dep_tree.py
rb/complexity/word/__init__.py
rb/complexity/word/factory.py
rb/complexity/word/name_entity.py
rb/complexity/word/name_entity_enum.py
rb/complexity/word/no_repetitions.py
rb/complexity/word/no_wd_paths_hypernym_tree.py
rb/complexity/word/polysemy.py
rb/complexity/word/unq_name_entity.py
rb/complexity/word/wd_avg_depth_hypernym_tree.py
rb/complexity/word/wd_diff_lemma.py
rb/complexity/word/wd_len.py
rb/complexity/word/wd_max_depth_hypernym_tree.py
rb/comprehension/__init__.py
rb/comprehension/cm_indexer.py
rb/comprehension/cm_word_distance_indexer.py
rb/comprehension/comprehension_model.py
rb/comprehension/utils/__init__.py
rb/comprehension/utils/distance_strategies/__init__.py
rb/comprehension/utils/distance_strategies/abstract_distance_strategy.py
rb/comprehension/utils/distance_strategies/cm_coref_indexer.py
rb/comprehension/utils/distance_strategies/cm_syntactic_graph.py
rb/comprehension/utils/distance_strategies/full_semantic_search_word_distance_strategy.py
rbpy_rb-0.4.9.dist-info/LICENSE.txt
rbpy_rb-0.4.9.dist-info/METADATA
rbpy_rb-0.4.9.dist-info/WHEEL
rbpy_rb-0.4.9.dist-info/dependency_links.txt
rbpy_rb-0.4.9.dist-info/top_level.txt
rbpy_rb-0.4.9.dist-info/RECORD
