Metadata-Version: 2.1
Name: rbpy-rb
Version: 0.4.9
Summary: ReaderBench library written in python
Home-page: https://git.readerbench.com/ReaderBench/Readerbench-python
Author: Woodcarver
Author-email: batpepastrama@gmail.com
License: UNKNOWN
Platform: UNKNOWN
Classifier: Programming Language :: Python :: 3
Classifier: License :: OSI Approved :: Apache Software License
Classifier: Operating System :: OS Independent
Requires-Dist: wheel
Requires-Dist: spacy (==2.1.3)
Requires-Dist: nltk
Requires-Dist: gensim
Requires-Dist: numpy
Requires-Dist: wget
Requires-Dist: pymorphy2
Requires-Dist: neuralcoref
Requires-Dist: joblib
